{"packages/cupertino_icons/assets/CupertinoIcons.ttf":["packages/cupertino_icons/assets/CupertinoIcons.ttf"],"assets/lato/Lato-Black.ttf":["assets/lato/Lato-Black.ttf"],"assets/lato/Lato-Bold.ttf":["assets/lato/Lato-Bold.ttf"],"assets/lato/Lato-Light.ttf":["assets/lato/Lato-Light.ttf"],"assets/lato/Lato-Regular.ttf":["assets/lato/Lato-Regular.ttf"],"assets/lottie/animation.json":["assets/lottie/animation.json"],"assets/arrow.png":["assets/arrow.png"],"assets/banner_unired.jpg":["assets/banner_unired.jpg"],"assets/banner_unired.png":["assets/banner_unired.png"],"assets/svg/cash.svg":["assets/svg/cash.svg"],"assets/svg/click.svg":["assets/svg/click.svg"],"assets/svg/delivery.svg":["assets/svg/delivery.svg"],"assets/arrows/down_left.svg":["assets/arrows/down_left.svg"],"assets/arrows/down_right.svg":["assets/arrows/down_right.svg"],"assets/english.svg":["assets/english.svg"],"assets/iOS-1.png":["assets/iOS-1.png"],"assets/iOS-2.png":["assets/iOS-2.png"],"assets/iOS-3.png":["assets/iOS-3.png"],"assets/iOS-4.png":["assets/iOS-4.png"],"assets/iOS-5.png":["assets/iOS-5.png"],"assets/iOS-6.png":["assets/iOS-6.png"],"assets/iOS.png":["assets/iOS.png"],"assets/ic_basket.png":["assets/ic_basket.png"],"assets/ic_basket.svg":["assets/ic_basket.svg"],"assets/svg/ic_cash_back.svg":["assets/svg/ic_cash_back.svg"],"assets/ic_delete.svg":["assets/ic_delete.svg"],"assets/svg/ic_discount.svg":["assets/svg/ic_discount.svg"],"assets/ic_empty_basket.png":["assets/ic_empty_basket.png"],"assets/ic_exit.svg":["assets/ic_exit.svg"],"assets/svg/ic_free_delivery.svg":["assets/svg/ic_free_delivery.svg"],"assets/ic_menu_favorites.svg":["assets/ic_menu_favorites.svg"],"assets/ic_menu_home.svg":["assets/ic_menu_home.svg"],"assets/ic_menu_profile.svg":["assets/ic_menu_profile.svg"],"assets/ic_menu_search.svg":["assets/ic_menu_search.svg"],"assets/ic_menu_shopping.svg":["assets/ic_menu_shopping.svg"],"assets/ic_notifications.svg":["assets/ic_notifications.svg"],"assets/ic_profile_1.svg":["assets/ic_profile_1.svg"],"assets/ic_profile_2.svg":["assets/ic_profile_2.svg"],"assets/ic_profile_3.svg":["assets/ic_profile_3.svg"],"assets/ic_profile_4.svg":["assets/ic_profile_4.svg"],"assets/ic_profile_5.svg":["assets/ic_profile_5.svg"],"assets/ic_profile_6.svg":["assets/ic_profile_6.svg"],"assets/ic_profile_7.svg":["assets/ic_profile_7.svg"],"assets/svg/ic_rectangle.svg":["assets/svg/ic_rectangle.svg"],"assets/ic_settings_cache.svg":["assets/ic_settings_cache.svg"],"assets/ic_settings_exit.svg":["assets/ic_settings_exit.svg"],"assets/ic_settings_language.svg":["assets/ic_settings_language.svg"],"assets/ic_settings_notification.svg":["assets/ic_settings_notification.svg"],"assets/ic_settings_sound.svg":["assets/ic_settings_sound.svg"],"assets/ic_shopping.png":["assets/ic_shopping.png"],"assets/icon_star.svg":["assets/icon_star.svg"],"assets/icon_toggle_star.svg":["assets/icon_toggle_star.svg"],"assets/img_category_1.png":["assets/img_category_1.png"],"assets/img_category_2.png":["assets/img_category_2.png"],"assets/img_category_3.png":["assets/img_category_3.png"],"assets/img_category_4.png":["assets/img_category_4.png"],"assets/img_category_5.png":["assets/img_category_5.png"],"assets/img_category_6.png":["assets/img_category_6.png"],"assets/img_category_7.png":["assets/img_category_7.png"],"assets/locale/localization_en.json":["assets/locale/localization_en.json"],"assets/locale/localization_ru.json":["assets/locale/localization_ru.json"],"assets/locale/localization_uz.json":["assets/locale/localization_uz.json"],"assets/location.svg":["assets/location.svg"],"assets/logo.svg":["assets/logo.svg"],"assets/logo_placeholder.svg":["assets/logo_placeholder.svg"],"assets/logo_text.svg":["assets/logo_text.svg"],"assets/svg/my.svg":["assets/svg/my.svg"],"assets/my_location.png":["assets/my_location.png"],"assets/svg/payme.svg":["assets/svg/payme.svg"],"assets/place.png":["assets/place.png"],"assets/placeholder_cover.jpg":["assets/placeholder_cover.jpg"],"assets/russia.svg":["assets/russia.svg"],"assets/scene_12.png":["assets/scene_12.png"],"assets/scene_14.png":["assets/scene_14.png"],"assets/scene_15.png":["assets/scene_15.png"],"assets/scene_18.png":["assets/scene_18.png"],"assets/scene_20.png":["assets/scene_20.png"],"assets/shop_icon.png":["assets/shop_icon.png"],"assets/svg/terminal.svg":["assets/svg/terminal.svg"],"assets/arrows/top_left.svg":["assets/arrows/top_left.svg"],"assets/arrows/top_right.svg":["assets/arrows/top_right.svg"],"assets/png/unired.png":["assets/png/unired.png"],"assets/svg/unired.svg":["assets/svg/unired.svg"],"assets/user.png":["assets/user.png"],"assets/uzbekistan.svg":["assets/uzbekistan.svg"],"assets/svg/uzcard.svg":["assets/svg/uzcard.svg"]}